django_eveonline_doctrine_manager
test
